<?xml version='1.0' encoding='UTF-8'?>
<xwikidoc version="1.1">
  <web>IRC</web>
  <name>medsavantArchive20130603</name>
  <language />
  <defaultLanguage />
  <translation>0</translation>
  <creator>XWiki.sdumitriu</creator>
  <creationDate>1370237052000</creationDate>
  <parent>IRC.WebHome</parent>
  <author>XWiki.sdumitriu</author>
  <contentAuthor>XWiki.sdumitriu</contentAuthor>
  <date>1370285358000</date>
  <contentUpdateDate>1370285358000</contentUpdateDate>
  <version>1.51</version>
  <title>IRC Archive for channel #medsavant on 03 June 2013</title>
  <comment>Logging from IRC</comment>
  <minorEdit>true</minorEdit>
  <syntaxId>plain/1.0</syntaxId>
  <hidden>false</hidden>
  <content>&lt;sdumitriu> has joined #medsavant
09:11 &lt;BogdanVancea> has joined #medsavant
09:12 &lt;bvancea> has joined #medsavant
09:13 &lt;bvancea> hello, sdumitriu
09:49 &lt;sdumitriu> Hi bvancea
09:50 &lt;bvancea> how are you? how was the weekend? :P
09:50 &lt;sdumitriu> Not as productive as I hoped
09:50 &lt;sdumitriu> I managed to get a basic DMG build for MedSavant, though
09:51 &lt;bvancea> nice
09:51 &lt;bvancea> :D
10:19 &lt;sdumitriu> So, what are your plans for this week?
10:22 &lt;bvancea> create an first index configuration for the variants
10:22 &lt;bvancea> and connect it to medsavant
10:22 &lt;bvancea> connect the index to medsavant*
10:24 &lt;sdumitriu> OK
10:24 &lt;sdumitriu> But you must make sure the index works decently before trying to connect it
10:24 &lt;bvancea> I want to make a better estimate, so I'll check the code and try make a plan for each day
10:25 &lt;bvancea> hmm... what are you refering to when saying "works decently"?
10:28 &lt;sdumitriu> You can run a query in under a second
10:28 &lt;bvancea> sure
10:29 &lt;bvancea> I'll start with tests then
10:29 &lt;bvancea> and only start actualy integration
10:29 &lt;bvancea> after I get decent results there
10:29 &lt;sdumitriu> Yep
10:29 &lt;sdumitriu> I'll try to get in contact with the other student today
10:30 &lt;sdumitriu> It's been a week already without any sign
10:30 &lt;bvancea> I check the GSOC webpage, he's doing some query parallelization
10:30 &lt;bvancea> checked*
10:30 &lt;sdumitriu> Yes
10:30 &lt;bvancea> perhaps he doesn't have internet at the moment
10:31 &lt;bvancea> is it common for students to not respond to emails during the community bonding period?
10:31 &lt;sdumitriu> No
10:31 &lt;bvancea> so it hasn't happened to you before?
10:31 &lt;sdumitriu> If they do that, they should be kicked out ASAP
10:31 &lt;sdumitriu> Nope
10:32 &lt;bvancea> I see
10:33 &lt;bvancea> and if this student doesn't respond, the slot is effectively wasted?
10:37 &lt;sdumitriu> No, we can get another student
10:37 &lt;sdumitriu> If we do that before the end of the bonding period
10:38 &lt;bvancea> oh, I see
10:39 &lt;bvancea> well, maybe this student will eventually respond
10:42 &lt;bvancea> well, I'll go have dinner
10:42 &lt;bvancea> then write the status email
10:42 &lt;sdumitriu> K
10:42 &lt;bvancea> and start working on the index
10:42 &lt;bvancea> bbl
12:37 &lt;sdumitriu1> has joined #medsavant
13:38 &lt;bvancea> Seems like the other student responded :)
13:39 &lt;sdumitriu1> Yes
14:49 &lt;bvancea> well, I'm off to shower and then to bed
14:49 &lt;bvancea> good night</content>
  <object>
    <name>IRC.medsavantArchive20130603</name>
    <number>0</number>
    <className>IRC.IRCBotArchiveClass</className>
    <guid>4ba56ac8-c8f3-48ba-a431-513ff5baee7c</guid>
    <class>
      <name>IRC.IRCBotArchiveClass</name>
      <customClass />
      <customMapping />
      <defaultViewSheet />
      <defaultEditSheet />
      <defaultWeb />
      <nameField />
      <validationScript />
      <channel>
        <customDisplay />
        <disabled>0</disabled>
        <name>channel</name>
        <number>1</number>
        <picker>0</picker>
        <prettyName>Channel</prettyName>
        <size>30</size>
        <unmodifiable>0</unmodifiable>
        <validationMessage />
        <validationRegExp />
        <classType>com.xpn.xwiki.objects.classes.StringClass</classType>
      </channel>
    </class>
    <property>
      <channel>medsavant</channel>
    </property>
  </object>
</xwikidoc>